cynn-0.1.5.dist-info/RECORD
cynn-0.1.5.dist-info/WHEEL
cynn-0.1.5.dist-info/METADATA
cynn-0.1.5.dist-info/licenses/LICENSE
cynn/tinn.cpython-313-darwin.so
cynn/CMakeLists.txt
cynn/cnn.cpython-313-darwin.so
cynn/__init__.py
cynn/fann.cpython-313-darwin.so
cynn/genann.cpython-313-darwin.so
cynn/kann.cpython-313-darwin.so
