Metadata-Version: 2.4
Name: cynn
Version: 0.1.5
Summary: Python bindings to five lightweight C neural network libraries (Tinn, GENANN, FANN, nn1, KANN).
Keywords: neural-network,machine-learning,deep-learning,cython,mlp,lstm,gru,rnn,cnn,backpropagation,artificial-intelligence
Author-Email: Shakeeb Alireza <me@example.com>
Maintainer-Email: Shakeeb Alireza <me@example.com>
License-Expression: GPL-3.0-or-later
Classifier: Development Status :: 4 - Beta
Classifier: Intended Audience :: Developers
Classifier: Intended Audience :: Education
Classifier: Intended Audience :: Science/Research
Classifier: Operating System :: OS Independent
Classifier: Programming Language :: Cython
Classifier: Programming Language :: Python :: 3
Classifier: Programming Language :: Python :: 3.11
Classifier: Programming Language :: Python :: 3.12
Classifier: Programming Language :: Python :: 3.13
Classifier: Programming Language :: Python :: 3.14
Classifier: Programming Language :: Python :: Implementation :: CPython
Classifier: Topic :: Scientific/Engineering :: Artificial Intelligence
Classifier: Topic :: Software Development :: Libraries :: Python Modules
Classifier: Typing :: Typed
Project-URL: Homepage, https://github.com/shakfu/cynn
Project-URL: Repository, https://github.com/shakfu/cynn
Project-URL: Issues, https://github.com/shakfu/cynn/issues
Requires-Python: >=3.10
